gitflow_visualizer/__init__.py
gitflow_visualizer/run.py
gitflow_visualizer-0.1.2.dist-info/METADATA
gitflow_visualizer-0.1.2.dist-info/WHEEL
gitflow_visualizer-0.1.2.dist-info/entry_points.txt
gitflow_visualizer-0.1.2.dist-info/licenses/LICENSE
gitflow_visualizer-0.1.2.dist-info/RECORD
