Metadata-Version: 2.3
Name: gitflow-visualizer
Version: 0.1.2
Summary: Visualize GitHub Repository Workflow Activities
Author-email: verssae <sparky@hanyang.ac.kr>
License: The MIT License (MIT)
License-File: LICENSE
Requires-Python: >=3.8
Requires-Dist: requests>=2.32.3
Requires-Dist: rich>=13.8.1
